MYgames/__init__.py
MYgames/__main__.py
MYgames/guess_animal.py
MYgames/memory.py
MYgames/rock_paper_scissors.py
MYgames-0.1.dist-info/LICENSE
MYgames-0.1.dist-info/METADATA
MYgames-0.1.dist-info/WHEEL
MYgames-0.1.dist-info/top_level.txt
MYgames-0.1.dist-info/RECORD
