Metadata-Version: 2.1
Name: MYgames
Version: 0.1
Summary: Simple games to play
Home-page: https://github.com/MandiYang/MYgames
Author: Mandi Yang
Author-email: yangmandi2008@gmail.com
License: MIT
Download-URL: https://github.com/MandiYang/MYgames/releases/download/0.1/MYgames.zip
Platform: UNKNOWN
Classifier: Programming Language :: Python :: 3
Classifier: License :: OSI Approved :: MIT License
Requires-Python: >=3.5
